{
	"animations": [
		{
			"offsets": [0, 0],
			"loop": false,
			"fps": 24,
			"anim": "idle",
			"indices": [],
			"name": "idle"
		},
		{
			"offsets": [202, 3],
			"loop": false,
			"fps": 24,
			"anim": "singLEFT",
			"indices": [],
			"name": "left"
		},
		{
			"offsets": [8, -14],
			"loop": false,
			"fps": 24,
			"anim": "singDOWN",
			"indices": [],
			"name": "down"
		},
		{
			"offsets": [3, 203],
			"loop": false,
			"fps": 24,
			"anim": "singUP",
			"indices": [],
			"name": "up"
		},
		{
			"offsets": [-2, 2],
			"loop": false,
			"fps": 24,
			"anim": "singRIGHT",
			"indices": [],
			"name": "right"
		}
	],
	"vocals_file": "",
	"no_antialiasing": false,
	"image": "characters/A8",
	"position": [650, 140],
	"healthicon": "face",
	"flip_x": false,
	"healthbar_colors": [135, 40, 40],
	"camera_position": [-270, -460],
	"sing_duration": 7.09999999999999,
	"scale": 2.2,
	"_editor_isPlayer": false
}